{
  "super-metroid": {
    "title": "Super Metroid",
    "cellSize": 256,
    "guessMapCellPx": 14,
    "areas": [
      {
        "id": "crateria",
        "name": "Crateria",
        "url": "https://www.snesmaps.com/maps/SuperMetroid/SuperMetroidMapCrateria.png",
        "ingameUrl": "https://vgmaps.de/files/snes/maps/super-metroid-crateria-in-game-map-snes-map.webp",
        "offsetX": 0,
        "offsetY": 0,
        "excludeCells": [
          [
            0,
            0
          ],
          [
            1,
            0
          ],
          [
            0,
            1
          ],
          [
            1,
            1
          ]
        ]
      },
      {
        "id": "brinstar",
        "name": "Brinstar",
        "url": "https://www.snesmaps.com/maps/SuperMetroid/SuperMetroidMapBrinstar.png",
        "ingameUrl": "https://vgmaps.de/files/snes/maps/super-metroid-brinstar-in-game-map-snes-map.webp",
        "offsetX": 0,
        "offsetY": 64,
        "excludeCells": [
          [
            0,
            0
          ],
          [
            1,
            0
          ],
          [
            0,
            1
          ],
          [
            1,
            1
          ],
          [
            4,
            0
          ]
        ],
        "includeCells": [
          [
            6,
            8
          ],
          [
            21,
            16
          ],
          [
            37,
            19
          ],
          [
            38,
            19
          ]
        ],
        "cellCropOffsets": {
          "38,19": [
            -29,
            250
          ]
        }
      },
      {
        "id": "norfair",
        "name": "Norfair",
        "url": "https://www.snesmaps.com/maps/SuperMetroid/SuperMetroidMapNorfair.png",
        "ingameUrl": "https://vgmaps.de/files/snes/maps/super-metroid-norfair-in-game-map-snes-map.webp",
        "offsetX": 0,
        "offsetY": 48,
        "excludeCells": [
          [
            0,
            0
          ],
          [
            1,
            0
          ],
          [
            2,
            0
          ],
          [
            3,
            0
          ]
        ],
        "includeCells": [
          [
            23,
            3
          ],
          [
            24,
            3
          ],
          [
            8,
            6
          ],
          [
            23,
            9
          ],
          [
            34,
            13
          ]
        ]
      },
      {
        "id": "wrecked-ship",
        "name": "Wrecked Ship",
        "url": "https://www.snesmaps.com/maps/SuperMetroid/SuperMetroidMapWreckedShip.png",
        "ingameUrl": "https://vgmaps.de/files/snes/maps/super-metroid-wrecked-ship-in-game-map-snes-map.webp",
        "offsetX": 128,
        "offsetY": 0,
        "excludeCells": [
          [
            0,
            0
          ],
          [
            1,
            0
          ],
          [
            0,
            1
          ],
          [
            1,
            1
          ]
        ]
      },
      {
        "id": "maridia",
        "name": "Maridia",
        "url": "https://www.snesmaps.com/maps/SuperMetroid/SuperMetroidMapMaridia.png",
        "ingameUrl": "https://vgmaps.de/files/snes/maps/super-metroid-maridia-in-game-map-snes-map.webp",
        "offsetX": 112,
        "offsetY": 48,
        "excludeCells": [
          [
            0,
            0
          ],
          [
            1,
            0
          ],
          [
            0,
            1
          ],
          [
            1,
            1
          ]
        ],
        "includeCells": [
          [
            3,
            7
          ],
          [
            0,
            9
          ],
          [
            1,
            10
          ],
          [
            2,
            10
          ],
          [
            3,
            10
          ],
          [
            4,
            10
          ],
          [
            5,
            10
          ],
          [
            6,
            10
          ],
          [
            2,
            11
          ],
          [
            3,
            11
          ],
          [
            4,
            11
          ],
          [
            5,
            11
          ],
          [
            6,
            11
          ],
          [
            1,
            12
          ],
          [
            0,
            13
          ],
          [
            1,
            13
          ],
          [
            4,
            13
          ],
          [
            0,
            14
          ],
          [
            1,
            14
          ],
          [
            0,
            15
          ],
          [
            0,
            16
          ]
        ]
      },
      {
        "id": "tourian",
        "name": "Tourian",
        "url": "https://www.snesmaps.com/maps/SuperMetroid/SuperMetroidMapTourian.png",
        "ingameUrl": "https://vgmaps.de/files/snes/maps/super-metroid-tourian-in-game-map-snes-map.webp",
        "offsetX": 0,
        "offsetY": 48,
        "excludeCells": [
          [
            0,
            0
          ],
          [
            1,
            0
          ],
          [
            0,
            1
          ],
          [
            1,
            1
          ]
        ]
      }
    ]
  }
}